{
  "project_info": {
    "project_number": "6586098523",
    "project_id": "najlepszapizzawmiescier",
    "storage_bucket": "najlepszapizzawmiescier.appspot.com"
  },
  "client": [
    {
      "client_info": {
        "mobilesdk_app_id": "1:6586098523:android:a96bfe15b0b6f22c54b07e",
        "android_client_info": {
          "package_name": "com.patrykbarszczewski.najlepsza_pizza_w_miescie"
        }
      },
      "oauth_client": [
        {
          "client_id": "6586098523-0djnl3q6ssampj8pot4sn3kqq104vmoi.apps.googleusercontent.com",
          "client_type": 3
        }
      ],
      "api_key": [
        {
          "current_key": "AIzaSyDSDwpvVemXzvBnFFJLE0o4Qi01Bk6H9gI"
        }
      ],
      "services": {
        "appinvite_service": {
          "other_platform_oauth_client": [
            {
              "client_id": "6586098523-0djnl3q6ssampj8pot4sn3kqq104vmoi.apps.googleusercontent.com",
              "client_type": 3
            }
          ]
        }
      }
    }
  ],
  "configuration_version": "1"
}